enos_subscribe/__init__.py
enos_subscribe/core.py
enos_subscribe/error.py
enos_subscribe/group.py
enos_subscribe/structs.py
enos_subscribe/ws.py
enos_subscribe/proto/__init__.py
enos_subscribe/proto/common_pb2.py
enos_subscribe/proto/sub_pb2.py
enos_subscribe/test/__init__.py
enos_subscribe/test/test_client.py
enos_subscribe/vendor/__init__.py
enos_subscribe/vendor/six.py
enos_subscribe-2.6.0.dist-info/METADATA
enos_subscribe-2.6.0.dist-info/WHEEL
enos_subscribe-2.6.0.dist-info/top_level.txt
enos_subscribe-2.6.0.dist-info/RECORD
